<?xml version="1.0" encoding="UTF-8"?>
<entity>
 <name>PipeHole</name>
 <attribute type="java.lang.Long" length="128" primary="TRUE" index="TRUE" nullable="FALSE" regex="">id</attribute>
 <attribute type="java.lang.String" length="50" primary="FALSE" index="FALSE" nullable="FALSE" regex="">label</attribute>
 <attribute type="java.lang.String" length="50" primary="FALSE" index="FALSE" nullable="TRUE" regex="">materialtype</attribute>
 <attribute type="java.lang.String" length="50" primary="FALSE" index="FALSE" nullable="TRUE" regex="">pipeHoleType</attribute>
 <attribute type="java.lang.String" length="50" primary="FALSE" index="FALSE" nullable="TRUE" regex="">usageDescription</attribute>
 <attribute type="java.lang.String" length="20" primary="FALSE" index="FALSE" nullable="TRUE" regex="">belongtype</attribute>
 <attribute type="java.lang.String" length="50" primary="FALSE" index="FALSE" nullable="TRUE" regex="">belongowner</attribute>
 <attribute type="java.lang.String" length="20" primary="FALSE" index="FALSE" nullable="TRUE" regex="">diameter</attribute>
 <attribute type="java.lang.String" length="20" primary="FALSE" index="FALSE" nullable="TRUE" regex="">color</attribute>
 <attribute type="java.lang.String" length="20" primary="FALSE" index="FALSE" nullable="TRUE" regex="">status</attribute>
</entity>